forkpy/__init__.py
forkpy/factory.py
forkpy-0.0.3.dist-info/DESCRIPTION.rst
forkpy-0.0.3.dist-info/METADATA
forkpy-0.0.3.dist-info/RECORD
forkpy-0.0.3.dist-info/WHEEL
forkpy-0.0.3.dist-info/metadata.json
forkpy-0.0.3.dist-info/top_level.txt
