Metadata-Version: 2.0
Name: forkpy
Version: 0.0.3
Summary: Multiprocessing framework.
Home-page: http://pypi.python.org/pypi/forkpy/
Author: Yohan Chalier
Author-email: yohan.chalier@gmail.com
License: GNU GPLv3
Platform: UNKNOWN
